rexdsl/__init__.py
rexdsl/core.py
rexdsl/tests/__init__.py
rexdsl/tests/test_1.py
rexdsl-0.0.3.dist-info/METADATA
rexdsl-0.0.3.dist-info/WHEEL
rexdsl-0.0.3.dist-info/top_level.txt
rexdsl-0.0.3.dist-info/RECORD
