Metadata-Version: 2.4
Name: rexdsl
Version: 0.0.3
Summary: custom regex dsl designed in rply for simplicity
Requires-Python: >=3.10
Requires-Dist: pytest>=8.4.2
Requires-Dist: regex>=2025.9.18
Requires-Dist: rply>=0.7.8
